{
  "metadata": {
    "generated_at": "2026-05-25T23:50:01",
    "n_repeats": 3,
    "required_scenarios_complete": true,
    "console_log": "C:\\Users\\Furkan\\Desktop\\dosya\\NetProbe-UDP-ReliableTransfer-main\\data\\logs\\experiment_console.log"
  },
  "scenario1_packet_size": [
    {
      "elapsed_sec": 0.023814916610717773,
      "elapsed_sec_std": 0.00044446051370109575,
      "throughput_bps": 3440666.498652589,
      "throughput_bps_std": 64751.10790396365,
      "goodput_bps": 3440666.498652589,
      "goodput_bps_std": 64751.10790396365,
      "loss_rate_pct": 0.0,
      "loss_rate_pct_std": 0.0,
      "retry_rate_pct": 0.0,
      "retry_rate_pct_std": 0.0,
      "avg_rtt_ms": 0.09583830833435059,
      "avg_rtt_ms_std": 0.03324954648153715,
      "sent_count": 40,
      "sent_count_std": 0.0,
      "ack_count": 40,
      "ack_count_std": 0.0,
      "timeout_count": 0,
      "timeout_count_std": 0.0,
      "retry_count": 0,
      "retry_count_std": 0.0,
      "label": "S1_pkt256",
      "success": true,
      "run_count": 3,
      "valid_run_count": 3,
      "failed_runs": [],
      "file_size": 10240,
      "total_packets": 40,
      "PACKET_SIZE": 256,
      "LOSS_RATE": 0.0,
      "TIMEOUT": 2.0,
      "file_size_kb": 10.0,
      "throughput_kbps": 3440.666498652589,
      "goodput_kbps": 3440.666498652589,
      "throughput_kbps_std": 64.75110790396366,
      "goodput_kbps_std": 64.75110790396366,
      "elapsed_std": 0.00044446051370109575,
      "retry_std": 0.0,
      "packet_size_b": 256
    },
    {
      "elapsed_sec": 0.011334578196207682,
      "elapsed_sec_std": 0.002959569082907175,
      "throughput_bps": 7629164.948227752,
      "throughput_bps_std": 2312513.0575083597,
      "goodput_bps": 7629164.948227752,
      "goodput_bps_std": 2312513.0575083597,
      "loss_rate_pct": 0.0,
      "loss_rate_pct_std": 0.0,
      "retry_rate_pct": 0.0,
      "retry_rate_pct_std": 0.0,
      "avg_rtt_ms": 0.014988581339518229,
      "avg_rtt_ms_std": 0.025960984413424353,
      "sent_count": 20,
      "sent_count_std": 0.0,
      "ack_count": 20,
      "ack_count_std": 0.0,
      "timeout_count": 0,
      "timeout_count_std": 0.0,
      "retry_count": 0,
      "retry_count_std": 0.0,
      "label": "S1_pkt512",
      "success": true,
      "run_count": 3,
      "valid_run_count": 3,
      "failed_runs": [],
      "file_size": 10240,
      "total_packets": 20,
      "PACKET_SIZE": 512,
      "LOSS_RATE": 0.0,
      "TIMEOUT": 2.0,
      "file_size_kb": 10.0,
      "throughput_kbps": 7629.164948227752,
      "goodput_kbps": 7629.164948227752,
      "throughput_kbps_std": 2312.5130575083595,
      "goodput_kbps_std": 2312.5130575083595,
      "elapsed_std": 0.002959569082907175,
      "retry_std": 0.0,
      "packet_size_b": 512
    },
    {
      "elapsed_sec": 0.011600891749064127,
      "elapsed_sec_std": 0.004999989235112108,
      "throughput_bps": 8354427.85283709,
      "throughput_bps_std": 4552141.435373202,
      "goodput_bps": 8354427.85283709,
      "goodput_bps_std": 4552141.435373202,
      "loss_rate_pct": 0.0,
      "loss_rate_pct_std": 0.0,
      "retry_rate_pct": 0.0,
      "retry_rate_pct_std": 0.0,
      "avg_rtt_ms": 0.0627279281616211,
      "avg_rtt_ms_std": 0.10864795862945834,
      "sent_count": 10,
      "sent_count_std": 0.0,
      "ack_count": 10,
      "ack_count_std": 0.0,
      "timeout_count": 0,
      "timeout_count_std": 0.0,
      "retry_count": 0,
      "retry_count_std": 0.0,
      "label": "S1_pkt1024",
      "success": true,
      "run_count": 3,
      "valid_run_count": 3,
      "failed_runs": [],
      "file_size": 10240,
      "total_packets": 10,
      "PACKET_SIZE": 1024,
      "LOSS_RATE": 0.0,
      "TIMEOUT": 2.0,
      "file_size_kb": 10.0,
      "throughput_kbps": 8354.42785283709,
      "goodput_kbps": 8354.42785283709,
      "throughput_kbps_std": 4552.141435373202,
      "goodput_kbps_std": 4552.141435373202,
      "elapsed_std": 0.004999989235112108,
      "retry_std": 0.0,
      "packet_size_b": 1024
    },
    {
      "elapsed_sec": 0.002454837163289388,
      "elapsed_sec_std": 0.002127865747593985,
      "throughput_bps": 14840401.510064753,
      "throughput_bps_std": 12863737.980687492,
      "goodput_bps": 14840401.510064753,
      "goodput_bps_std": 12863737.980687492,
      "loss_rate_pct": 0.0,
      "loss_rate_pct_std": 0.0,
      "retry_rate_pct": 0.0,
      "retry_rate_pct_std": 0.0,
      "avg_rtt_ms": 0.0,
      "avg_rtt_ms_std": 0.0,
      "sent_count": 3,
      "sent_count_std": 0.0,
      "ack_count": 3,
      "ack_count_std": 0.0,
      "timeout_count": 0,
      "timeout_count_std": 0.0,
      "retry_count": 0,
      "retry_count_std": 0.0,
      "label": "S1_pkt4096",
      "success": true,
      "run_count": 3,
      "valid_run_count": 3,
      "failed_runs": [],
      "file_size": 10240,
      "total_packets": 3,
      "PACKET_SIZE": 4096,
      "LOSS_RATE": 0.0,
      "TIMEOUT": 2.0,
      "file_size_kb": 10.0,
      "throughput_kbps": 14840.401510064752,
      "goodput_kbps": 14840.401510064752,
      "throughput_kbps_std": 12863.737980687492,
      "goodput_kbps_std": 12863.737980687492,
      "elapsed_std": 0.002127865747593985,
      "retry_std": 0.0,
      "packet_size_b": 4096
    }
  ],
  "scenario2_timeout": [
    {
      "elapsed_sec": 0.34752098719278973,
      "elapsed_sec_std": 0.29146884664379913,
      "throughput_bps": 2576615.874858009,
      "throughput_bps_std": 4160115.9921802664,
      "goodput_bps": 2566023.611692588,
      "goodput_bps_std": 4169288.992485805,
      "loss_rate_pct": 6.666666666666667,
      "loss_rate_pct_std": 5.773502691896257,
      "retry_rate_pct": 6.666666666666667,
      "retry_rate_pct_std": 5.773502691896257,
      "avg_rtt_ms": 0.21318594614664713,
      "avg_rtt_ms_std": 0.20209446236524817,
      "sent_count": 10,
      "sent_count_std": 0.0,
      "ack_count": 10,
      "ack_count_std": 0.0,
      "timeout_count": 0.6666666666666666,
      "timeout_count_std": 0.5773502691896257,
      "retry_count": 0.6666666666666666,
      "retry_count_std": 0.5773502691896257,
      "label": "S2_to0.5",
      "success": true,
      "run_count": 3,
      "valid_run_count": 3,
      "failed_runs": [],
      "file_size": 10240,
      "total_packets": 10,
      "TIMEOUT": 0.5,
      "LOSS_RATE": 0.05,
      "PACKET_SIZE": 1024,
      "file_size_kb": 10.0,
      "throughput_kbps": 2576.615874858009,
      "goodput_kbps": 2566.023611692588,
      "throughput_kbps_std": 4160.115992180266,
      "goodput_kbps_std": 4169.288992485805,
      "elapsed_std": 0.29146884664379913,
      "retry_std": 0.5773502691896257,
      "timeout_sec": 0.5
    },
    {
      "elapsed_sec": 0.6792607307434082,
      "elapsed_sec_std": 0.5798421980276978,
      "throughput_bps": 2868546.305549327,
      "throughput_bps_std": 4814548.510563757,
      "goodput_bps": 2863160.5220010565,
      "goodput_bps_std": 4819212.735453376,
      "loss_rate_pct": 6.666666666666667,
      "loss_rate_pct_std": 5.773502691896257,
      "retry_rate_pct": 6.666666666666667,
      "retry_rate_pct_std": 5.773502691896257,
      "avg_rtt_ms": 0.040117899576822914,
      "avg_rtt_ms_std": 0.03856423526371642,
      "sent_count": 10,
      "sent_count_std": 0.0,
      "ack_count": 10,
      "ack_count_std": 0.0,
      "timeout_count": 0.6666666666666666,
      "timeout_count_std": 0.5773502691896257,
      "retry_count": 0.6666666666666666,
      "retry_count_std": 0.5773502691896257,
      "label": "S2_to1.0",
      "success": true,
      "run_count": 3,
      "valid_run_count": 3,
      "failed_runs": [],
      "file_size": 10240,
      "total_packets": 10,
      "TIMEOUT": 1.0,
      "LOSS_RATE": 0.05,
      "PACKET_SIZE": 1024,
      "file_size_kb": 10.0,
      "throughput_kbps": 2868.546305549327,
      "goodput_kbps": 2863.1605220010565,
      "throughput_kbps_std": 4814.548510563757,
      "goodput_kbps_std": 4819.212735453376,
      "elapsed_std": 0.5798421980276978,
      "retry_std": 0.5773502691896257,
      "timeout_sec": 1.0
    },
    {
      "elapsed_sec": 0.007057666778564453,
      "elapsed_sec_std": 0.0016940051106694247,
      "throughput_bps": 12097369.426134093,
      "throughput_bps_std": 3088690.097888819,
      "goodput_bps": 12097369.426134093,
      "goodput_bps_std": 3088690.097888819,
      "loss_rate_pct": 0.0,
      "loss_rate_pct_std": 0.0,
      "retry_rate_pct": 0.0,
      "retry_rate_pct_std": 0.0,
      "avg_rtt_ms": 0.07549126942952473,
      "avg_rtt_ms_std": 0.06690124882342308,
      "sent_count": 10,
      "sent_count_std": 0.0,
      "ack_count": 10,
      "ack_count_std": 0.0,
      "timeout_count": 0,
      "timeout_count_std": 0.0,
      "retry_count": 0,
      "retry_count_std": 0.0,
      "label": "S2_to2.0",
      "success": true,
      "run_count": 3,
      "valid_run_count": 3,
      "failed_runs": [],
      "file_size": 10240,
      "total_packets": 10,
      "TIMEOUT": 2.0,
      "LOSS_RATE": 0.05,
      "PACKET_SIZE": 1024,
      "file_size_kb": 10.0,
      "throughput_kbps": 12097.369426134093,
      "goodput_kbps": 12097.369426134093,
      "throughput_kbps_std": 3088.690097888819,
      "goodput_kbps_std": 3088.690097888819,
      "elapsed_std": 0.0016940051106694247,
      "retry_std": 0.0,
      "timeout_sec": 2.0
    },
    {
      "elapsed_sec": 5.017904122670491,
      "elapsed_sec_std": 5.003897988505519,
      "throughput_bps": 1850822.5437659088,
      "throughput_bps_std": 3181669.8741943375,
      "goodput_bps": 1849733.2802194506,
      "goodput_bps_std": 3182613.204355761,
      "loss_rate_pct": 10.0,
      "loss_rate_pct_std": 10.0,
      "retry_rate_pct": 10.0,
      "retry_rate_pct_std": 10.0,
      "avg_rtt_ms": 0.05585352579752604,
      "avg_rtt_ms_std": 0.04912201771785416,
      "sent_count": 10,
      "sent_count_std": 0.0,
      "ack_count": 10,
      "ack_count_std": 0.0,
      "timeout_count": 1,
      "timeout_count_std": 1.0,
      "retry_count": 1,
      "retry_count_std": 1.0,
      "label": "S2_to5.0",
      "success": true,
      "run_count": 3,
      "valid_run_count": 3,
      "failed_runs": [],
      "file_size": 10240,
      "total_packets": 10,
      "TIMEOUT": 5.0,
      "LOSS_RATE": 0.05,
      "PACKET_SIZE": 1024,
      "file_size_kb": 10.0,
      "throughput_kbps": 1850.822543765909,
      "goodput_kbps": 1849.7332802194505,
      "throughput_kbps_std": 3181.6698741943374,
      "goodput_kbps_std": 3182.613204355761,
      "elapsed_std": 5.003897988505519,
      "retry_std": 1.0,
      "timeout_sec": 5.0
    }
  ],
  "scenario3_loss": [
    {
      "elapsed_sec": 0.01213526725769043,
      "elapsed_sec_std": 0.004852909713975882,
      "throughput_bps": 7827076.247601387,
      "throughput_bps_std": 4043766.490456859,
      "goodput_bps": 7827076.247601387,
      "goodput_bps_std": 4043766.490456859,
      "loss_rate_pct": 0.0,
      "loss_rate_pct_std": 0.0,
      "retry_rate_pct": 0.0,
      "retry_rate_pct_std": 0.0,
      "avg_rtt_ms": 0.08753140767415364,
      "avg_rtt_ms_std": 0.15160884534965843,
      "sent_count": 10,
      "sent_count_std": 0.0,
      "ack_count": 10,
      "ack_count_std": 0.0,
      "timeout_count": 0,
      "timeout_count_std": 0.0,
      "retry_count": 0,
      "retry_count_std": 0.0,
      "label": "S3_loss0pct",
      "success": true,
      "run_count": 3,
      "valid_run_count": 3,
      "failed_runs": [],
      "file_size": 10240,
      "total_packets": 10,
      "LOSS_RATE": 0.0,
      "PACKET_SIZE": 1024,
      "TIMEOUT": 2.0,
      "file_size_kb": 10.0,
      "throughput_kbps": 7827.076247601387,
      "goodput_kbps": 7827.076247601387,
      "throughput_kbps_std": 4043.766490456859,
      "goodput_kbps_std": 4043.766490456859,
      "elapsed_std": 0.004852909713975882,
      "retry_std": 0.0,
      "loss_rate_configured_pct": 0.0
    },
    {
      "elapsed_sec": 2.0155413150787354,
      "elapsed_sec_std": 2.011336613853513,
      "throughput_bps": 3504316.5658363295,
      "throughput_bps_std": 6009681.948602103,
      "goodput_bps": 3501601.86104808,
      "goodput_bps_std": 6012032.936496414,
      "loss_rate_pct": 10.0,
      "loss_rate_pct_std": 10.0,
      "retry_rate_pct": 10.0,
      "retry_rate_pct_std": 10.0,
      "avg_rtt_ms": 0.06976127624511719,
      "avg_rtt_ms_std": 0.06143677626012257,
      "sent_count": 10,
      "sent_count_std": 0.0,
      "ack_count": 10,
      "ack_count_std": 0.0,
      "timeout_count": 1,
      "timeout_count_std": 1.0,
      "retry_count": 1,
      "retry_count_std": 1.0,
      "label": "S3_loss5pct",
      "success": true,
      "run_count": 3,
      "valid_run_count": 3,
      "failed_runs": [],
      "file_size": 10240,
      "total_packets": 10,
      "LOSS_RATE": 0.05,
      "PACKET_SIZE": 1024,
      "TIMEOUT": 2.0,
      "file_size_kb": 10.0,
      "throughput_kbps": 3504.3165658363296,
      "goodput_kbps": 3501.60186104808,
      "throughput_kbps_std": 6009.681948602103,
      "goodput_kbps_std": 6012.032936496415,
      "elapsed_std": 2.011336613853513,
      "retry_std": 1.0,
      "loss_rate_configured_pct": 5.0
    },
    {
      "elapsed_sec": 4.028274377187093,
      "elapsed_sec_std": 2.0060696496397656,
      "throughput_bps": 28877.848658582465,
      "throughput_bps_std": 14022.510550778568,
      "goodput_bps": 24813.843862584785,
      "goodput_bps_std": 14031.909954560668,
      "loss_rate_pct": 20.0,
      "loss_rate_pct_std": 10.0,
      "retry_rate_pct": 20.0,
      "retry_rate_pct_std": 10.0,
      "avg_rtt_ms": 0.010021527608235678,
      "avg_rtt_ms_std": 0.017357794986918404,
      "sent_count": 10,
      "sent_count_std": 0.0,
      "ack_count": 10,
      "ack_count_std": 0.0,
      "timeout_count": 2,
      "timeout_count_std": 1.0,
      "retry_count": 2,
      "retry_count_std": 1.0,
      "label": "S3_loss15pct",
      "success": true,
      "run_count": 3,
      "valid_run_count": 3,
      "failed_runs": [],
      "file_size": 10240,
      "total_packets": 10,
      "LOSS_RATE": 0.15,
      "PACKET_SIZE": 1024,
      "TIMEOUT": 2.0,
      "file_size_kb": 10.0,
      "throughput_kbps": 28.877848658582465,
      "goodput_kbps": 24.813843862584786,
      "throughput_kbps_std": 14.022510550778568,
      "goodput_kbps_std": 14.031909954560668,
      "elapsed_std": 2.0060696496397656,
      "retry_std": 1.0,
      "loss_rate_configured_pct": 15.0
    },
    {
      "elapsed_sec": 9.03017270565033,
      "elapsed_sec_std": 9.92923493303271,
      "throughput_bps": 27018.778821102933,
      "throughput_bps_std": 25218.50674190598,
      "goodput_bps": 22938.631962428983,
      "goodput_bps_std": 25222.44847596496,
      "loss_rate_pct": 45.0,
      "loss_rate_pct_std": 49.49747468305833,
      "retry_rate_pct": 45.0,
      "retry_rate_pct_std": 49.49747468305833,
      "avg_rtt_ms": 0.0723123550415039,
      "avg_rtt_ms_std": 0.04727190528981875,
      "sent_count": 10,
      "sent_count_std": 0.0,
      "ack_count": 10,
      "ack_count_std": 0.0,
      "timeout_count": 4.5,
      "timeout_count_std": 4.949747468305833,
      "retry_count": 4.5,
      "retry_count_std": 4.949747468305833,
      "label": "S3_loss30pct",
      "success": true,
      "run_count": 3,
      "valid_run_count": 2,
      "failed_runs": [
        {
          "label": "S3_loss30pct_r1",
          "success": false,
          "error": "S3_loss30pct_r1 did not complete cleanly: {'filename': 'test_10KB.bin', 'file_size': 10240, 'total_packets': 10, 'sent_count': 9, 'ack_count': 9, 'timeout_count': 13, 'retry_count': 12, 'drop_count': 13, 'failed_packets': [0], 'rtt_list': [0.0, 0.5021095275878906, 0.0, 0.0, 0.4909038543701172, 0.0, 0.0, 0.0, 0.5002021789550781], 'start_time': 1779742099.2138116, 'end_time': 1779742125.3397493, 'elapsed_sec': 26.125937700271606, 'throughput_bps': 6898.278717020992, 'goodput_bps': 2822.023111508588, 'loss_rate_pct': 144.44444444444443, 'retry_rate_pct': 120.0, 'avg_rtt_ms': 0.165912840101454, 'fin_acked': False, 'success': False, 'label': 'S3_loss30pct_r1', 'LOSS_RATE': 0.3, 'PACKET_SIZE': 1024, 'TIMEOUT': 2.0}",
          "LOSS_RATE": 0.3,
          "PACKET_SIZE": 1024,
          "TIMEOUT": 2.0
        }
      ],
      "file_size": 10240,
      "total_packets": 10,
      "LOSS_RATE": 0.3,
      "PACKET_SIZE": 1024,
      "TIMEOUT": 2.0,
      "file_size_kb": 10.0,
      "throughput_kbps": 27.018778821102934,
      "goodput_kbps": 22.938631962428982,
      "throughput_kbps_std": 25.21850674190598,
      "goodput_kbps_std": 25.22244847596496,
      "elapsed_std": 9.92923493303271,
      "retry_std": 4.949747468305833,
      "loss_rate_configured_pct": 30.0
    }
  ],
  "scenario4_filesize": [
    {
      "elapsed_sec": 0.009115060170491537,
      "elapsed_sec_std": 0.00203930358952597,
      "throughput_bps": 9297938.334220845,
      "throughput_bps_std": 2100117.715301364,
      "goodput_bps": 9297938.334220845,
      "goodput_bps_std": 2100117.715301364,
      "loss_rate_pct": 0.0,
      "loss_rate_pct_std": 0.0,
      "retry_rate_pct": 0.0,
      "retry_rate_pct_std": 0.0,
      "avg_rtt_ms": 0.03571510314941406,
      "avg_rtt_ms_std": 0.04218198096807778,
      "sent_count": 10,
      "sent_count_std": 0.0,
      "ack_count": 10,
      "ack_count_std": 0.0,
      "timeout_count": 0,
      "timeout_count_std": 0.0,
      "retry_count": 0,
      "retry_count_std": 0.0,
      "label": "S4_10KB",
      "success": true,
      "run_count": 3,
      "valid_run_count": 3,
      "failed_runs": [],
      "file_size": 10240,
      "total_packets": 10,
      "PACKET_SIZE": 1024,
      "TIMEOUT": 2.0,
      "LOSS_RATE": 0.0,
      "file_size_kb": 10.0,
      "throughput_kbps": 9297.938334220846,
      "goodput_kbps": 9297.938334220846,
      "throughput_kbps_std": 2100.117715301364,
      "goodput_kbps_std": 2100.117715301364,
      "elapsed_std": 0.00203930358952597,
      "retry_std": 0.0
    },
    {
      "elapsed_sec": 0.0543829600016276,
      "elapsed_sec_std": 0.0021418740311078075,
      "throughput_bps": 15079253.90740924,
      "throughput_bps_std": 598535.8365140379,
      "goodput_bps": 15079253.90740924,
      "goodput_bps_std": 598535.8365140379,
      "loss_rate_pct": 0.0,
      "loss_rate_pct_std": 0.0,
      "retry_rate_pct": 0.0,
      "retry_rate_pct_std": 0.0,
      "avg_rtt_ms": 0.08148670196533203,
      "avg_rtt_ms_std": 0.06916404422801138,
      "sent_count": 100,
      "sent_count_std": 0.0,
      "ack_count": 100,
      "ack_count_std": 0.0,
      "timeout_count": 0,
      "timeout_count_std": 0.0,
      "retry_count": 0,
      "retry_count_std": 0.0,
      "label": "S4_100KB",
      "success": true,
      "run_count": 3,
      "valid_run_count": 3,
      "failed_runs": [],
      "file_size": 102400,
      "total_packets": 100,
      "PACKET_SIZE": 1024,
      "TIMEOUT": 2.0,
      "LOSS_RATE": 0.0,
      "file_size_kb": 100.0,
      "throughput_kbps": 15079.25390740924,
      "goodput_kbps": 15079.25390740924,
      "throughput_kbps_std": 598.5358365140379,
      "goodput_kbps_std": 598.5358365140379,
      "elapsed_std": 0.0021418740311078075,
      "retry_std": 0.0
    },
    {
      "elapsed_sec": 0.5869308312733968,
      "elapsed_sec_std": 0.04360895223057175,
      "throughput_bps": 14346317.141167229,
      "throughput_bps_std": 1090693.5842788923,
      "goodput_bps": 14346317.141167229,
      "goodput_bps_std": 1090693.5842788923,
      "loss_rate_pct": 0.0,
      "loss_rate_pct_std": 0.0,
      "retry_rate_pct": 0.0,
      "retry_rate_pct_std": 0.0,
      "avg_rtt_ms": 0.06145394096771876,
      "avg_rtt_ms_std": 0.017168817666471926,
      "sent_count": 1024,
      "sent_count_std": 0.0,
      "ack_count": 1024,
      "ack_count_std": 0.0,
      "timeout_count": 0,
      "timeout_count_std": 0.0,
      "retry_count": 0,
      "retry_count_std": 0.0,
      "label": "S4_1024KB",
      "success": true,
      "run_count": 3,
      "valid_run_count": 3,
      "failed_runs": [],
      "file_size": 1048576,
      "total_packets": 1024,
      "PACKET_SIZE": 1024,
      "TIMEOUT": 2.0,
      "LOSS_RATE": 0.0,
      "file_size_kb": 1024.0,
      "throughput_kbps": 14346.317141167228,
      "goodput_kbps": 14346.317141167228,
      "throughput_kbps_std": 1090.6935842788923,
      "goodput_kbps_std": 1090.6935842788923,
      "elapsed_std": 0.04360895223057175,
      "retry_std": 0.0
    },
    {
      "elapsed_sec": 5.783211787541707,
      "elapsed_sec_std": 0.05874533532630062,
      "throughput_bps": 14506106.260456134,
      "throughput_bps_std": 148217.3249474507,
      "goodput_bps": 14506106.260456134,
      "goodput_bps_std": 148217.3249474507,
      "loss_rate_pct": 0.0,
      "loss_rate_pct_std": 0.0,
      "retry_rate_pct": 0.0,
      "retry_rate_pct_std": 0.0,
      "avg_rtt_ms": 0.06266559939831495,
      "avg_rtt_ms_std": 0.004826496642450319,
      "sent_count": 10240,
      "sent_count_std": 0.0,
      "ack_count": 10240,
      "ack_count_std": 0.0,
      "timeout_count": 0,
      "timeout_count_std": 0.0,
      "retry_count": 0,
      "retry_count_std": 0.0,
      "label": "S4_10240KB",
      "success": true,
      "run_count": 3,
      "valid_run_count": 3,
      "failed_runs": [],
      "file_size": 10485760,
      "total_packets": 10240,
      "PACKET_SIZE": 1024,
      "TIMEOUT": 2.0,
      "LOSS_RATE": 0.0,
      "file_size_kb": 10240.0,
      "throughput_kbps": 14506.106260456134,
      "goodput_kbps": 14506.106260456134,
      "throughput_kbps_std": 148.2173249474507,
      "goodput_kbps_std": 148.2173249474507,
      "elapsed_std": 0.05874533532630062,
      "retry_std": 0.0
    }
  ],
  "saw_vs_gbn": {
    "saw": [
      {
        "filename": "test_10KB.bin",
        "file_size": 10240,
        "total_packets": 10,
        "sent_count": 10,
        "ack_count": 10,
        "timeout_count": 0,
        "retry_count": 0,
        "drop_count": 0,
        "failed_packets": [],
        "start_time": 1779742198.820425,
        "end_time": 1779742198.8360338,
        "elapsed_sec": 0.015608787536621094,
        "throughput_bps": 5248325.650394086,
        "goodput_bps": 5248325.650394086,
        "loss_rate_pct": 0.0,
        "retry_rate_pct": 0.0,
        "avg_rtt_ms": 0.16810894012451172,
        "fin_acked": true,
        "success": true,
        "file_size_kb": 10.0,
        "throughput_kbps": 5248.325650394086,
        "goodput_kbps": 5248.325650394086
      },
      {
        "filename": "test_100KB.bin",
        "file_size": 102400,
        "total_packets": 100,
        "sent_count": 100,
        "ack_count": 100,
        "timeout_count": 0,
        "retry_count": 0,
        "drop_count": 0,
        "failed_packets": [],
        "start_time": 1779742199.3570282,
        "end_time": 1779742199.412625,
        "elapsed_sec": 0.05559682846069336,
        "throughput_bps": 14734653.444830395,
        "goodput_bps": 14734653.444830395,
        "loss_rate_pct": 0.0,
        "retry_rate_pct": 0.0,
        "avg_rtt_ms": 0.07119178771972656,
        "fin_acked": true,
        "success": true,
        "file_size_kb": 100.0,
        "throughput_kbps": 14734.653444830396,
        "goodput_kbps": 14734.653444830396
      }
    ],
    "gbn": [
      {
        "filename": "test_10KB.bin",
        "file_size": 10240,
        "file_size_kb": 10.0,
        "total_packets": 10,
        "window_size": 4,
        "sent_count": 10,
        "ack_count": 10,
        "timeout_count": 0,
        "retry_count": 0,
        "drop_count": 0,
        "failed_packets": [],
        "elapsed_sec": 0.015173196792602539,
        "throughput_bps": 5398994.1025439575,
        "goodput_bps": 5398994.1025439575,
        "throughput_kbps": 5398.9941025439575,
        "goodput_kbps": 5398.9941025439575,
        "loss_rate_pct": 0.0,
        "retry_rate_pct": 0.0,
        "avg_rtt_ms": 5.140137672424316,
        "fin_acked": true,
        "success": true,
        "protocol": "GBN"
      },
      {
        "filename": "test_100KB.bin",
        "file_size": 102400,
        "file_size_kb": 100.0,
        "total_packets": 100,
        "window_size": 4,
        "sent_count": 100,
        "ack_count": 100,
        "timeout_count": 0,
        "retry_count": 0,
        "drop_count": 0,
        "failed_packets": [],
        "elapsed_sec": 0.055463552474975586,
        "throughput_bps": 14770060.03842996,
        "goodput_bps": 14770060.03842996,
        "throughput_kbps": 14770.060038429961,
        "goodput_kbps": 14770.060038429961,
        "loss_rate_pct": 0.0,
        "retry_rate_pct": 0.0,
        "avg_rtt_ms": 1.838691234588623,
        "fin_acked": true,
        "success": true,
        "protocol": "GBN"
      }
    ]
  },
  "udp_vs_tcp": {
    "udp": [
      {
        "filename": "test_10KB.bin",
        "file_size": 10240,
        "total_packets": 10,
        "sent_count": 10,
        "ack_count": 10,
        "timeout_count": 0,
        "retry_count": 0,
        "drop_count": 0,
        "failed_packets": [],
        "start_time": 1779742198.820425,
        "end_time": 1779742198.8360338,
        "elapsed_sec": 0.015608787536621094,
        "throughput_bps": 5248325.650394086,
        "goodput_bps": 5248325.650394086,
        "loss_rate_pct": 0.0,
        "retry_rate_pct": 0.0,
        "avg_rtt_ms": 0.16810894012451172,
        "fin_acked": true,
        "success": true,
        "file_size_kb": 10.0,
        "throughput_kbps": 5248.325650394086,
        "goodput_kbps": 5248.325650394086
      },
      {
        "filename": "test_100KB.bin",
        "file_size": 102400,
        "total_packets": 100,
        "sent_count": 100,
        "ack_count": 100,
        "timeout_count": 0,
        "retry_count": 0,
        "drop_count": 0,
        "failed_packets": [],
        "start_time": 1779742199.3570282,
        "end_time": 1779742199.412625,
        "elapsed_sec": 0.05559682846069336,
        "throughput_bps": 14734653.444830395,
        "goodput_bps": 14734653.444830395,
        "loss_rate_pct": 0.0,
        "retry_rate_pct": 0.0,
        "avg_rtt_ms": 0.07119178771972656,
        "fin_acked": true,
        "success": true,
        "file_size_kb": 100.0,
        "throughput_kbps": 14734.653444830396,
        "goodput_kbps": 14734.653444830396
      }
    ],
    "tcp": [
      {
        "filename": "test_10KB.bin",
        "file_size": 10240,
        "file_size_kb": 10.0,
        "elapsed_sec": 0.0,
        "throughput_bps": 0,
        "goodput_bps": 0,
        "throughput_kbps": 0.0,
        "goodput_kbps": 0.0,
        "protocol": "TCP",
        "integrity_ok": true
      },
      {
        "filename": "test_100KB.bin",
        "file_size": 102400,
        "file_size_kb": 100.0,
        "elapsed_sec": 0.0,
        "throughput_bps": 0,
        "goodput_bps": 0,
        "throughput_kbps": 0.0,
        "goodput_kbps": 0.0,
        "protocol": "TCP",
        "integrity_ok": true
      }
    ]
  }
}